fugw/__init__.py
fugw/utils.py
fugw/mappings/__init__.py
fugw/mappings/barycenter.py
fugw/mappings/dense.py
fugw/mappings/sparse.py
fugw/mappings/utils.py
fugw/scripts/coarse_to_fine.py
fugw/scripts/lmds.py
fugw/solvers/__init__.py
fugw/solvers/dense.py
fugw/solvers/sparse.py
fugw/solvers/utils.py
fugw-0.1.1.dist-info/LICENSE
fugw-0.1.1.dist-info/METADATA
fugw-0.1.1.dist-info/WHEEL
fugw-0.1.1.dist-info/top_level.txt
fugw-0.1.1.dist-info/RECORD
