Metadata-Version: 2.1
Name: fugw
Version: 0.1.1
Summary: A collection of gpu-compatible solvers for fused unbalanced gromov-wasserstein optimization problems
Author-email: Alexis Thual <alexisthual@gmail.com>, Huy Tran <quang-huy.tran@univ-ubs.fr>
Project-URL: homepage, https://github.com/alexisthual/fugw
Project-URL: repository, https://github.com/alexisthual/fugw.git
Keywords: optimal transport,gromov wasserstein,solver
Classifier: Programming Language :: Python :: 3
Classifier: License :: OSI Approved :: MIT License
Classifier: Operating System :: OS Independent
Requires-Python: >=3.7
License-File: LICENSE
Requires-Dist: dijkstra3d >=1.12.1
Requires-Dist: joblib >=1.2.0
Requires-Dist: numpy >=1.20
Requires-Dist: rich >=13.3.1
Requires-Dist: POT >=0.9.0
Requires-Dist: scikit-learn
Requires-Dist: scipy
Requires-Dist: torch >=1.12
Requires-Dist: tvb-gdist >=2.1.1
Provides-Extra: dev
Requires-Dist: black ; extra == 'dev'
Requires-Dist: fugw[doc] ; extra == 'dev'
Requires-Dist: fugw[test] ; extra == 'dev'
Requires-Dist: pre-commit ; extra == 'dev'
Provides-Extra: doc
Requires-Dist: furo >=2022.12.07 ; extra == 'doc'
Requires-Dist: fugw[test] ; extra == 'doc'
Requires-Dist: kaleido ; extra == 'doc'
Requires-Dist: m2r2 ; extra == 'doc'
Requires-Dist: matplotlib ; extra == 'doc'
Requires-Dist: memory-profiler ; extra == 'doc'
Requires-Dist: myst-parser ; extra == 'doc'
Requires-Dist: numpydoc ; extra == 'doc'
Requires-Dist: pillow ; extra == 'doc'
Requires-Dist: plotly ; extra == 'doc'
Requires-Dist: sphinx ==5.3.0 ; extra == 'doc'
Requires-Dist: sphinx-copybutton ; extra == 'doc'
Requires-Dist: sphinx-gallery >=0.11.1 ; extra == 'doc'
Provides-Extra: test
Requires-Dist: flake8 ; extra == 'test'
Requires-Dist: nilearn ; extra == 'test'
Requires-Dist: pyproject-flake8 ; extra == 'test'
Requires-Dist: pytest >=7.2 ; extra == 'test'
